suyo/__init__.py
suyo/core.py
suyo-1.3.6.dist-info/licenses/LICENSE
suyo-1.3.6.dist-info/METADATA
suyo-1.3.6.dist-info/WHEEL
suyo-1.3.6.dist-info/top_level.txt
suyo-1.3.6.dist-info/RECORD
