Metadata-Version: 2.4
Name: suyo
Version: 1.3.6
Summary: Suyo - essential helper package for HamzaGSopp projects
Author: HamzaGSopp
License: MIT License
Requires-Python: >=3.8
License-File: LICENSE
Requires-Dist: fs>=2.4
Dynamic: license-file
